setup.py
fmq/__init__.py
fmq.egg-info/PKG-INFO
fmq.egg-info/SOURCES.txt
fmq.egg-info/dependency_links.txt
fmq.egg-info/not-zip-safe
fmq.egg-info/top_level.txt