Metadata-Version: 1.0
Name: fmq
Version: 0.1
Summary: Fast MP Queue, Feed Me Queue
Home-page: https://github.com/weitang114/FMQ
Author: Tang Lee
Author-email: weitang114@gmail.com
License: MIT
Platform: UNKNOWN
